brainflow/__init__.py
brainflow/board_shim.py
brainflow/data_filter.py
brainflow/exit_codes.py
brainflow/ml_model.py
brainflow/utils.py
brainflow/lib/BoardController.dll
brainflow/lib/BoardController32.dll
brainflow/lib/BrainBitLib.dll
brainflow/lib/BrainBitLib32.dll
brainflow/lib/BrainFlowBluetooth.dll
brainflow/lib/BrainFlowBluetooth32.dll
brainflow/lib/DataHandler.dll
brainflow/lib/DataHandler32.dll
brainflow/lib/GanglionLib.dll
brainflow/lib/GanglionLib32.dll
brainflow/lib/MLModule.dll
brainflow/lib/MuseLib.dll
brainflow/lib/MuseLib32.dll
brainflow/lib/SynchroniLib.dll
brainflow/lib/SynchroniLib32.dll
brainflow/lib/Unicorn.dll
brainflow/lib/eego-SDK.dll
brainflow/lib/eego-SDK32.dll
brainflow/lib/gForceSDKWrapper.dll
brainflow/lib/gForceSDKWrapper32.dll
brainflow/lib/gforce32.dll
brainflow/lib/gforce64.dll
brainflow/lib/libBoardController.dylib
brainflow/lib/libBoardController.so
brainflow/lib/libBrainBitLib.dylib
brainflow/lib/libBrainBitLib.so
brainflow/lib/libBrainFlowBluetooth.dylib
brainflow/lib/libBrainFlowBluetooth.so
brainflow/lib/libDataHandler.dylib
brainflow/lib/libDataHandler.so
brainflow/lib/libGanglionLib.dylib
brainflow/lib/libGanglionLib.so
brainflow/lib/libMLModule.dylib
brainflow/lib/libMLModule.so
brainflow/lib/libMuseLib.dylib
brainflow/lib/libMuseLib.so
brainflow/lib/libSynchroniLib.dylib
brainflow/lib/libSynchroniLib_x64.so
brainflow/lib/libeego-SDK.so
brainflow/lib/libneurosdk-shared.dylib
brainflow/lib/libonnxruntime_arm64.dylib
brainflow/lib/libonnxruntime_x64.so
brainflow/lib/libsensor_x64.so
brainflow/lib/libsimpleble-c.dylib
brainflow/lib/libsimpleble-c.so
brainflow/lib/libunicorn.so
brainflow/lib/libunicorn_raspberry.so
brainflow/lib/neurosdk-x64.dll
brainflow/lib/neurosdk-x86.dll
brainflow/lib/onnxruntime_x64.dll
brainflow/lib/onnxruntime_x86.dll
brainflow/lib/sensor.dll
brainflow/lib/sensor32.dll
brainflow/lib/simpleble-c.dll
brainflow/lib/simpleble-c32.dll
brainflow-5.20.1.dist-info/LICENSE.txt
brainflow-5.20.1.dist-info/METADATA
brainflow-5.20.1.dist-info/WHEEL
brainflow-5.20.1.dist-info/top_level.txt
brainflow-5.20.1.dist-info/zip-safe
brainflow-5.20.1.dist-info/RECORD
