Metadata-Version: 2.1
Name: brainflow
Version: 5.20.1
Summary: Python Binding for BrainFlow
Home-page: https://github.com/brainflow-dev/brainflow
Author: Andrey Parfenov
Author-email: andrey@brainflow.org
Requires-Python: >=3.5.6
License-File: LICENSE.txt
Requires-Dist: numpy
Requires-Dist: setuptools
